{"cols":[{"label":"Coin","type":"string"},{"label":"Algo","type":"string"},{"label":"Blocks","type":"number"},{"label":"Difficulty","type":"number"},{"label":"Reward","type":"number"},{"label":"Best Price(BTC)","type":"string"},{"label":"Exchange","type":"string"},{"label":"% Profitability of BTC","type":"number"},{"label":"Profitability % Adj for Stales","type":"number"},{"label":"Avg Profitability Past 7 Days","type":"number"}],"rows":[{"c":[{"v":"<img src='\/img\/Feathercoin.png' width='16' height='16' alt='Feathercoin'\/><strong>Feathercoin<\/strong>"},{"v":"scrypt"},{"v":35137},{"v":66.527},{"v":200},{"v":"<a href='https:\/\/btc-e.com'\/>0.00109<\/a>"},{"v":"<a href='https:\/\/btc-e.com'\/>BTC-e<\/a>"},{"v":204.55},{"v":199.39},{"v":111.05}]},{"c":[{"v":"<img src='\/img\/MEMcoin.png' width='16' height='16' alt='MemeCoin'\/><strong>MemeCoin<\/strong>"},{"v":"scrypt"},{"v":42006},{"v":0.48192815},{"v":100},{"v":"<a href='https:\/\/www.cryptsy.com\/'\/>0.00001444<\/a>"},{"v":"<a href='https:\/\/www.cryptsy.com\/'\/>Cryptsy<\/a>"},{"v":187.04},{"v":157.17},{"v":121.84}]},{"c":[{"v":"<img src='\/img\/Worldcoin.png' width='16' height='16' alt='Worldcoin'\/><strong>Worldcoin<\/strong>"},{"v":"scrypt"},{"v":153803},{"v":1.21957347},{"v":32},{"v":"<a href='http:\/\/www.mcxnow.com\/'\/>0.00011<\/a>"},{"v":"<a href='http:\/\/www.mcxnow.com\/'\/>mcxNOW<\/a>"},{"v":180.17},{"v":121.12},{"v":134.72}]},{"c":[{"v":"<img src='\/img\/Digitalcoin.png' width='16' height='16' alt='DigitalCoin'\/><strong>DigitalCoin<\/strong>"},{"v":"scrypt"},{"v":100249},{"v":3.297},{"v":20},{"v":"<a href='https:\/\/www.cryptsy.com\/'\/>0.000365505<\/a>"},{"v":"<a href='https:\/\/www.cryptsy.com\/'\/>Cryptsy<\/a>"},{"v":138.4},{"v":104.32},{"v":143.67}]},{"c":[{"v":"<img src='\/img\/FastCoin.png' width='16' height='16' alt='Fastcoin'\/><strong>Fastcoin<\/strong>"},{"v":"scrypt"},{"v":92737},{"v":0.10855593},{"v":32},{"v":"<a href='https:\/\/www.cryptsy.com\/'\/>0.00000751<\/a>"},{"v":"<a href='https:\/\/www.cryptsy.com\/'\/>Cryptsy<\/a>"},{"v":138.19},{"v":81.29},{"v":153.87}]},{"c":[{"v":"<img src='\/img\/Litecoin.png' width='16' height='16' alt='Litecoin'\/><strong>Litecoin<\/strong>"},{"v":"scrypt"},{"v":368742},{"v":638.53306792},{"v":50},{"v":"<a href='https:\/\/bter.com\/ref\/929'\/>0.0233755<\/a>"},{"v":"<a href='https:\/\/bter.com\/ref\/929'\/>Bter.com<\/a>"},{"v":114.26},{"v":111.38},{"v":112.07}]},{"c":[{"v":"<img src='\/img\/Luckycoin.png' width='16' height='16' alt='Luckycoin'\/><strong>Luckycoin<\/strong>"},{"v":"scrypt"},{"v":24319},{"v":1.154},{"v":88},{"v":"<a href='https:\/\/www.cryptsy.com\/'\/>0.00002403<\/a>"},{"v":"<a href='https:\/\/www.cryptsy.com\/'\/>Cryptsy<\/a>"},{"v":114.39},{"v":105.73},{"v":115.06}]},{"c":[{"v":"<img src='\/img\/BBQCoin.png' width='16' height='16' alt='BBQCoin'\/><strong>BBQCoin<\/strong>"},{"v":"scrypt"},{"v":445812},{"v":1.023},{"v":42},{"v":"<a href='https:\/\/bter.com\/ref\/929'\/>0.0000427<\/a>"},{"v":"<a href='https:\/\/bter.com\/ref\/929'\/>Bter.com<\/a>"},{"v":109.43},{"v":101.16},{"v":107.06}]},{"c":[{"v":"<img src='\/img\/Mincoin.png' width='16' height='16' alt='Mincoin'\/><strong>Mincoin<\/strong>"},{"v":"scrypt"},{"v":85059},{"v":0.506},{"v":2},{"v":"<a href='http:\/\/www.mcxnow.com\/'\/>0.00044001<\/a>"},{"v":"<a href='http:\/\/www.mcxnow.com\/'\/>mcxNOW<\/a>"},{"v":108.56},{"v":100.35},{"v":101.94}]},{"c":[{"v":"<img src='\/img\/PPCoin.png' width='16' height='16' alt='PPCoin'\/><strong>PPCoin<\/strong>"},{"v":"SHA-256"},{"v":52479},{"v":291601.779},{"v":430.28779348772},{"v":"<a href='https:\/\/btc-e.com'\/>0.00114<\/a>"},{"v":"<a href='https:\/\/btc-e.com'\/>BTC-e<\/a>"},{"v":105.01},{"v":105.01},{"v":99.39}]},{"c":[{"v":"<img src='\/img\/Novacoin.png' width='16' height='16' alt='Novacoin'\/><strong>Novacoin<\/strong>"},{"v":"scrypt"},{"v":25965},{"v":206.27},{"v":10.46},{"v":"<a href='https:\/\/www.cryptsy.com\/'\/>0.033<\/a>"},{"v":"<a href='https:\/\/www.cryptsy.com\/'\/>Cryptsy<\/a>"},{"v":104.46},{"v":104.46},{"v":110.38}]},{"c":[{"v":"<img src='\/img\/Bitcoin.png' width='16' height='16' alt='Bitcoin'\/><strong>Bitcoin<\/strong>"},{"v":"SHA-256"},{"v":240848},{"v":15605632.681286},{"v":25},{"v":"<a href=''\/>1<\/a>"},{"v":"<a href=''\/><\/a>"},{"v":100},{"v":100},{"v":100}]},{"c":[{"v":"<img src='\/img\/Bitbar.png' width='16' height='16' alt='BitBar'\/><strong>BitBar<\/strong>"},{"v":"scrypt"},{"v":11082},{"v":11.166},{"v":0.16722083558206},{"v":"<a href='https:\/\/www.cryptsy.com\/'\/>0.1<\/a>"},{"v":"<a href='https:\/\/www.cryptsy.com\/'\/>Cryptsy<\/a>"},{"v":93.48},{"v":93.48},{"v":109.27}]},{"c":[{"v":"<img src='\/img\/Freicoin.png' width='16' height='16' alt='Freicoin'\/><strong>Freicoin<\/strong>"},{"v":"SHA-256"},{"v":29058},{"v":24798.162},{"v":225.85900565951},{"v":"<a href='https:\/\/bter.com\/ref\/929'\/>0.000164<\/a>"},{"v":"<a href='https:\/\/bter.com\/ref\/929'\/>Bter.com<\/a>"},{"v":93.24},{"v":93.24},{"v":89.58}]},{"c":[{"v":"<img src='\/img\/Franko.png' width='16' height='16' alt='Franko'\/><strong>Franko<\/strong>"},{"v":"scrypt"},{"v":77148},{"v":0.244},{"v":0.25},{"v":"<a href='https:\/\/www.cryptsy.com\/'\/>0.00143153<\/a>"},{"v":"<a href='https:\/\/www.cryptsy.com\/'\/>Cryptsy<\/a>"},{"v":91.56},{"v":76.94},{"v":102.28}]},{"c":[{"v":"<img src='\/img\/Nibble.png' width='16' height='16' alt='Nibble'\/><strong>Nibble<\/strong>"},{"v":"scrypt"},{"v":21819},{"v":1.79892945},{"v":50},{"v":"<a href='https:\/\/www.cryptsy.com\/'\/>0.0000523<\/a>"},{"v":"<a href='https:\/\/www.cryptsy.com\/'\/>Cryptsy<\/a>"},{"v":90.74},{"v":88.45},{"v":99.02}]},{"c":[{"v":"<img src='\/img\/Terracoin.png' width='16' height='16' alt='Terracoin'\/><strong>Terracoin<\/strong>"},{"v":"SHA-256"},{"v":143329},{"v":27664.994270478},{"v":20},{"v":"<a href='https:\/\/btc-e.com'\/>0.00178<\/a>"},{"v":"<a href='https:\/\/btc-e.com'\/>BTC-e<\/a>"},{"v":80.33},{"v":77.63},{"v":89.75}]},{"c":[{"v":"<img src='\/img\/CHNcoin.png' width='16' height='16' alt='CHNCoin'\/><strong>CHNCoin<\/strong>"},{"v":"scrypt"},{"v":58091},{"v":41.82101451},{"v":88},{"v":"<a href='https:\/\/btc-e.com'\/>0.00049<\/a>"},{"v":"<a href='https:\/\/btc-e.com'\/>BTC-e<\/a>"},{"v":64.36},{"v":59.49},{"v":53.69}]},{"c":[{"v":"<img src='\/img\/Phenixcoin.png' width='16' height='16' alt='Phenixcoin'\/><strong>Phenixcoin<\/strong>"},{"v":"scrypt"},{"v":46078},{"v":10.39087419},{"v":50},{"v":"<a href='https:\/\/www.cryptsy.com\/'\/>0.000155<\/a>"},{"v":"<a href='https:\/\/www.cryptsy.com\/'\/>Cryptsy<\/a>"},{"v":46.56},{"v":45.38},{"v":95.87}]},{"c":[{"v":"<img src='\/img\/AmericanCoin.png' width='16' height='16' alt='AmericanCoin'\/><strong>AmericanCoin<\/strong>"},{"v":"scrypt"},{"v":17496},{"v":3.27936581},{"v":100},{"v":"<a href='https:\/\/www.cryptsy.com\/'\/>0.00002207<\/a>"},{"v":"<a href='https:\/\/www.cryptsy.com\/'\/>Cryptsy<\/a>"},{"v":42.01},{"v":38.83},{"v":79.6}]},{"c":[{"v":"<img src='\/img\/Elacoin.png' width='16' height='16' alt='Elacoin'\/><strong>Elacoin<\/strong>"},{"v":"scrypt"},{"v":21666},{"v":0.88827293},{"v":0.89972508400211},{"v":"<a href='https:\/\/www.cryptsy.com\/'\/>0.000511<\/a>"},{"v":"<a href='https:\/\/www.cryptsy.com\/'\/>Cryptsy<\/a>"},{"v":32.31},{"v":31.22},{"v":48.52}]},{"c":[{"v":"<img src='\/img\/Powercoin.png' width='16' height='16' alt='Powercoin'\/><strong>Powercoin<\/strong>"},{"v":"scrypt"},{"v":28715},{"v":1.6299806},{"v":40},{"v":"<a href='https:\/\/www.cryptsy.com\/'\/>0.000010403333333333<\/a>"},{"v":"<a href='https:\/\/www.cryptsy.com\/'\/>Cryptsy<\/a>"},{"v":15.94},{"v":13.39},{"v":16.87}]},{"c":[{"v":"<img src='\/img\/Hypercoin.png' width='16' height='16' alt='Hypercoin'\/><strong>Hypercoin<\/strong>"},{"v":"scrypt"},{"v":20246},{"v":2.35204261},{"v":25},{"v":"<a href='https:\/\/www.cryptsy.com\/'\/>0.000020146<\/a>"},{"v":"<a href='https:\/\/www.cryptsy.com\/'\/>Cryptsy<\/a>"},{"v":13.37},{"v":11.8},{"v":39.62}]},{"c":[{"v":"<img src='\/img\/Namecoin.png' width='16' height='16' alt='Namecoin'\/><strong>Namecoin<\/strong>"},{"v":"SHA-256"},{"v":115183},{"v":3047241.098},{"v":50},{"v":"<a href='https:\/\/btc-e.com'\/>0.00558<\/a>"},{"v":"<a href='https:\/\/btc-e.com'\/>BTC-e<\/a>"},{"v":5.72},{"v":5.72},{"v":5.67}]},{"c":[{"v":"<img src='\/img\/Ixcoin.png' width='16' height='16' alt='IXCoin'\/><strong>IXCoin<\/strong>"},{"v":"SHA-256"},{"v":141038},{"v":526933.57277972},{"v":96},{"v":"<a href='https:\/\/www.cryptsy.com\/'\/>0.00005<\/a>"},{"v":"<a href='https:\/\/www.cryptsy.com\/'\/>Cryptsy<\/a>"},{"v":0.57},{"v":0.57},{"v":0.59}]},{"c":[{"v":"<img src='\/img\/Devcoin.png' width='16' height='16' alt='Devcoin'\/><strong>Devcoin<\/strong>"},{"v":"SHA-256"},{"v":93031},{"v":1058839.485},{"v":5000},{"v":"<a href='https:\/\/www.cryptsy.com\/'\/>0.0000012<\/a>"},{"v":"<a href='https:\/\/www.cryptsy.com\/'\/>Cryptsy<\/a>"},{"v":0.35},{"v":0.35},{"v":0.44}]}]}